sudodog/__init__.py
sudodog/benchmark/__init__.py
sudodog/benchmark/api.py
sudodog/benchmark/display.py
sudodog/benchmark/gui.py
sudodog/benchmark/main.py
sudodog/benchmark/proxy.py
sudodog/benchmark/runner.py
sudodog/benchmark/test_suite.py
sudodog/benchmark/tester.py
sudodog/cli/__init__.py
sudodog/cli/main.py
sudodog/core/__init__.py
sudodog/core/access.py
sudodog/core/config.py
sudodog/core/exec_blocker.c
sudodog/core/exec_blocker.py
sudodog/core/guardrails.py
sudodog/core/telemetry.py
sudodog/core/telemetry_ws.py
sudodog/sandbox/__init__.py
sudodog/sandbox/base.py
sudodog/sandbox/docker.py
sudodog/sandbox/factory.py
sudodog/sandbox/linux.py
sudodog/sandbox/macos.py
sudodog/sandbox/windows.py
sudodog/scanner/__init__.py
sudodog/scanner/cli.py
sudodog/scanner/scanner.py
sudodog/utils/__init__.py
sudodog-2.7.6.dist-info/METADATA
sudodog-2.7.6.dist-info/WHEEL
sudodog-2.7.6.dist-info/entry_points.txt
sudodog-2.7.6.dist-info/top_level.txt
sudodog-2.7.6.dist-info/RECORD
