Metadata-Version: 2.4
Name: sudodog
Version: 2.7.6
Summary: Monitor and secure AI agents with guardrails. Pre-execution command blocking, PII filtering, and real-time security enforcement.
Author-email: SudoDog <hello@sudodog.com>
License: MIT
Project-URL: Homepage, https://sudodog.com
Project-URL: Source, https://github.com/SudoDog-official/SudoDog
Project-URL: Documentation, https://sudodog.com/docs
Project-URL: Dashboard, https://sudodog.com/dashboard
Keywords: ai,agents,monitoring,observability,security,access-control,permissions,langchain,autogpt,crewai,llm,openai,anthropic,claude
Classifier: Development Status :: 4 - Beta
Classifier: Intended Audience :: Developers
Classifier: Topic :: Security
Classifier: Topic :: Software Development :: Libraries :: Python Modules
Classifier: License :: OSI Approved :: MIT License
Classifier: Programming Language :: Python :: 3
Classifier: Programming Language :: Python :: 3.8
Classifier: Programming Language :: Python :: 3.9
Classifier: Programming Language :: Python :: 3.10
Classifier: Programming Language :: Python :: 3.11
Classifier: Programming Language :: Python :: 3.12
Classifier: Operating System :: OS Independent
Classifier: Operating System :: Microsoft :: Windows
Classifier: Operating System :: POSIX :: Linux
Classifier: Operating System :: MacOS :: MacOS X
Requires-Python: >=3.8
Requires-Dist: requests>=2.28.0
Requires-Dist: psutil>=5.9.0
Requires-Dist: pywin32>=305; platform_system == "Windows"
